alpss/__init__.py
alpss/alpss_auto_run.py
alpss/alpss_main.py
alpss/alpss_run.ipynb
alpss/alpss_run.py
alpss/alpss_study.py
alpss/alpss_watcher.py
alpss/carrier_filter.py
alpss/carrier_frequency.py
alpss/commands.py
alpss/full_uncertainty_analysis.py
alpss/instantaneous_uncertainty_analysis.py
alpss/num_derivative.py
alpss/plotting.py
alpss/saving.py
alpss/smoothing.py
alpss/spall_analysis.py
alpss/spall_doi_finder.py
alpss/utils.py
alpss/validation.py
alpss/velocity_calculation.py
alpss-1.3.2.dist-info/METADATA
alpss-1.3.2.dist-info/WHEEL
alpss-1.3.2.dist-info/entry_points.txt
alpss-1.3.2.dist-info/licenses/LICENSE
alpss-1.3.2.dist-info/RECORD
