Metadata-Version: 2.4
Name: alpss
Version: 1.3.2
Summary: Automated analysis of photonic Doppler velocimetry spall signals with uncertainty
License: GPL-3
License-File: LICENSE
Keywords: material science,spall
Author: Jake Diamond
Author-email: jdiamo15@jhu.edu
Maintainer: Jake Diamond
Maintainer-email: jdiamo15@jhu.edu
Requires-Python: >=3.9,<3.11
Classifier: Development Status :: 3 - Alpha
Classifier: Intended Audience :: Science/Research
Classifier: License :: OSI Approved :: GNU General Public License v3 (GPLv3)
Classifier: License :: Other/Proprietary License
Classifier: Natural Language :: English
Classifier: Operating System :: OS Independent
Classifier: Programming Language :: Python :: 3
Classifier: Programming Language :: Python :: 3.9
Classifier: Programming Language :: Python :: 3.10
Classifier: Topic :: Scientific/Engineering
Requires-Dist: IPython
Requires-Dist: findiff
Requires-Dist: matplotlib
Requires-Dist: numpy (>=1.17)
Requires-Dist: opencv-python
Requires-Dist: pandas
Requires-Dist: pytest (>=8.3.4,<9.0.0)
Requires-Dist: scipy (>1.12)
Requires-Dist: watchdog
